[
    {
        "metagame_event_id": "1",
        "type": "1",
        "experience_bonus": "30",
        "duration_minutes": "90"
    },
    {
        "metagame_event_id": "2",
        "type": "1",
        "experience_bonus": "30",
        "duration_minutes": "90"
    },
    {
        "metagame_event_id": "3",
        "type": "1",
        "experience_bonus": "30",
        "duration_minutes": "90"
    },
    {
        "metagame_event_id": "4",
        "type": "1",
        "experience_bonus": "30",
        "duration_minutes": "90"
    },
    {
        "metagame_event_id": "7",
        "type": "2",
        "duration_minutes": "45"
    },
    {
        "metagame_event_id": "8",
        "type": "2",
        "duration_minutes": "45"
    },
    {
        "metagame_event_id": "9",
        "type": "2",
        "duration_minutes": "45"
    },
    {
        "metagame_event_id": "10",
        "type": "2",
        "duration_minutes": "45"
    },
    {
        "metagame_event_id": "11",
        "type": "2",
        "duration_minutes": "45"
    },
    {
        "metagame_event_id": "12",
        "type": "2",
        "duration_minutes": "45"
    },
    {
        "metagame_event_id": "13",
        "type": "2",
        "duration_minutes": "45"
    },
    {
        "metagame_event_id": "14",
        "type": "2",
        "duration_minutes": "45"
    },
    {
        "metagame_event_id": "16",
        "type": "2",
        "duration_minutes": "45"
    },
    {
        "metagame_event_id": "17",
        "type": "2",
        "duration_minutes": "45"
    },
    {
        "metagame_event_id": "18",
        "type": "2",
        "duration_minutes": "45"
    },
    {
        "metagame_event_id": "106",
        "type": "6",
        "duration_minutes": "120"
    },
    {
        "metagame_event_id": "123",
        "type": "8",
        "experience_bonus": "30",
        "duration_minutes": "45"
    },
    {
        "metagame_event_id": "124",
        "type": "8",
        "experience_bonus": "30",
        "duration_minutes": "45"
    },
    {
        "metagame_event_id": "125",
        "type": "8",
        "experience_bonus": "30",
        "duration_minutes": "45"
    },
    {
        "metagame_event_id": "126",
        "type": "8",
        "experience_bonus": "30",
        "duration_minutes": "45"
    },
    {
        "metagame_event_id": "127",
        "type": "8",
        "experience_bonus": "30",
        "duration_minutes": "45"
    },
    {
        "metagame_event_id": "128",
        "type": "8",
        "experience_bonus": "30",
        "duration_minutes": "45"
    },
    {
        "metagame_event_id": "129",
        "type": "8",
        "experience_bonus": "30",
        "duration_minutes": "45"
    },
    {
        "metagame_event_id": "130",
        "type": "8",
        "experience_bonus": "30",
        "duration_minutes": "45"
    },
    {
        "metagame_event_id": "131",
        "type": "8",
        "experience_bonus": "30",
        "duration_minutes": "45"
    },
    {
        "metagame_event_id": "132",
        "type": "8",
        "experience_bonus": "30",
        "duration_minutes": "45"
    },
    {
        "metagame_event_id": "133",
        "type": "8",
        "experience_bonus": "30",
        "duration_minutes": "45"
    },
    {
        "metagame_event_id": "134",
        "type": "8",
        "experience_bonus": "30",
        "duration_minutes": "45"
    },
    {
        "metagame_event_id": "147",
        "type": "9",
        "experience_bonus": "25",
        "duration_minutes": "90"
    },
    {
        "metagame_event_id": "148",
        "type": "9",
        "experience_bonus": "25",
        "duration_minutes": "90"
    },
    {
        "metagame_event_id": "149",
        "type": "9",
        "experience_bonus": "25",
        "duration_minutes": "90"
    },
    {
        "metagame_event_id": "150",
        "type": "9",
        "experience_bonus": "25",
        "duration_minutes": "90"
    },
    {
        "metagame_event_id": "151",
        "type": "9",
        "experience_bonus": "25",
        "duration_minutes": "90"
    },
    {
        "metagame_event_id": "152",
        "type": "9",
        "experience_bonus": "25",
        "duration_minutes": "90"
    },
    {
        "metagame_event_id": "153",
        "type": "9",
        "experience_bonus": "25",
        "duration_minutes": "90"
    },
    {
        "metagame_event_id": "154",
        "type": "9",
        "experience_bonus": "25",
        "duration_minutes": "90"
    },
    {
        "metagame_event_id": "155",
        "type": "9",
        "experience_bonus": "25",
        "duration_minutes": "90"
    },
    {
        "metagame_event_id": "156",
        "type": "9",
        "experience_bonus": "25",
        "duration_minutes": "90"
    },
    {
        "metagame_event_id": "157",
        "type": "9",
        "experience_bonus": "25",
        "duration_minutes": "90"
    },
    {
        "metagame_event_id": "158",
        "type": "9",
        "experience_bonus": "25",
        "duration_minutes": "90"
    },
    {
        "metagame_event_id": "159",
        "type": "5",
        "duration_minutes": "10"
    },
    {
        "metagame_event_id": "160",
        "type": "5",
        "duration_minutes": "10"
    },
    {
        "metagame_event_id": "161",
        "type": "5",
        "duration_minutes": "10"
    },
    {
        "metagame_event_id": "162",
        "type": "5",
        "duration_minutes": "10"
    },
    {
        "metagame_event_id": "164",
        "type": "2",
        "duration_minutes": "60"
    },
    {
        "metagame_event_id": "167",
        "type": "10",
        "duration_minutes": "30"
    },
    {
        "metagame_event_id": "168",
        "type": "10",
        "duration_minutes": "45"
    },
    {
        "metagame_event_id": "170",
        "type": "5",
        "duration_minutes": "45"
    },
    {
        "metagame_event_id": "172",
        "type": "10",
        "duration_minutes": "30"
    },
    {
        "metagame_event_id": "173",
        "type": "10",
        "duration_minutes": "30"
    },
    {
        "metagame_event_id": "174",
        "type": "10",
        "duration_minutes": "30"
    },
    {
        "metagame_event_id": "175",
        "type": "10",
        "duration_minutes": "30"
    },
    {
        "metagame_event_id": "176",
        "type": "9",
        "experience_bonus": "25",
        "duration_minutes": "45"
    },
    {
        "metagame_event_id": "177",
        "type": "9",
        "experience_bonus": "25",
        "duration_minutes": "45"
    },
    {
        "metagame_event_id": "178",
        "type": "9",
        "experience_bonus": "25",
        "duration_minutes": "45"
    },
    {
        "metagame_event_id": "179",
        "type": "9",
        "experience_bonus": "25",
        "duration_minutes": "45"
    },
    {
        "metagame_event_id": "180",
        "type": "2",
        "duration_minutes": "45"
    },
    {
        "metagame_event_id": "181",
        "type": "2",
        "duration_minutes": "45"
    },
    {
        "metagame_event_id": "182",
        "type": "2",
        "duration_minutes": "45"
    },
    {
        "metagame_event_id": "183",
        "type": "2",
        "duration_minutes": "45"
    },
    {
        "metagame_event_id": "186",
        "type": "9",
        "experience_bonus": "25",
        "duration_minutes": "45"
    },
    {
        "metagame_event_id": "187",
        "type": "9",
        "experience_bonus": "25",
        "duration_minutes": "45"
    },
    {
        "metagame_event_id": "188",
        "type": "9",
        "experience_bonus": "25",
        "duration_minutes": "45"
    },
    {
        "metagame_event_id": "189",
        "type": "9",
        "experience_bonus": "25",
        "duration_minutes": "45"
    },
    {
        "metagame_event_id": "190",
        "type": "9",
        "experience_bonus": "25",
        "duration_minutes": "45"
    },
    {
        "metagame_event_id": "191",
        "type": "9",
        "experience_bonus": "25",
        "duration_minutes": "45"
    },
    {
        "metagame_event_id": "192",
        "type": "9",
        "experience_bonus": "25",
        "duration_minutes": "45"
    },
    {
        "metagame_event_id": "193",
        "type": "9",
        "experience_bonus": "25",
        "duration_minutes": "45"
    },
    {
        "metagame_event_id": "194",
        "type": "10",
        "duration_minutes": "45"
    },
    {
        "metagame_event_id": "195",
        "type": "10",
        "duration_minutes": "45"
    },
    {
        "metagame_event_id": "196",
        "type": "10",
        "duration_minutes": "45"
    },
    {
        "metagame_event_id": "197",
        "type": "10",
        "duration_minutes": "45"
    },
    {
        "metagame_event_id": "198",
        "type": "6",
        "duration_minutes": "30"
    },
    {
        "metagame_event_id": "199",
        "type": "6",
        "duration_minutes": "30"
    },
    {
        "metagame_event_id": "200",
        "type": "6",
        "duration_minutes": "30"
    },
    {
        "metagame_event_id": "201",
        "type": "6",
        "duration_minutes": "30"
    },
    {
        "metagame_event_id": "204",
        "type": "10",
        "duration_minutes": "10"
    },
    {
        "metagame_event_id": "205",
        "type": "4",
        "duration_minutes": "20"
    },
    {
        "metagame_event_id": "206",
        "type": "10",
        "duration_minutes": "2"
    },
    {
        "metagame_event_id": "207",
        "type": "10",
        "duration_minutes": "60"
    },
    {
        "metagame_event_id": "208",
        "type": "9",
        "experience_bonus": "25",
        "duration_minutes": "45"
    },
    {
        "metagame_event_id": "209",
        "type": "9",
        "experience_bonus": "25",
        "duration_minutes": "45"
    },
    {
        "metagame_event_id": "210",
        "type": "9",
        "experience_bonus": "25",
        "duration_minutes": "45"
    },
    {
        "metagame_event_id": "211",
        "type": "9",
        "experience_bonus": "25",
        "duration_minutes": "90"
    },
    {
        "metagame_event_id": "212",
        "type": "9",
        "experience_bonus": "25",
        "duration_minutes": "90"
    },
    {
        "metagame_event_id": "213",
        "type": "9",
        "experience_bonus": "25",
        "duration_minutes": "90"
    },
    {
        "metagame_event_id": "214",
        "type": "9",
        "experience_bonus": "25",
        "duration_minutes": "90"
    },
    {
        "metagame_event_id": "215",
        "type": "9",
        "experience_bonus": "25",
        "duration_minutes": "45"
    },
    {
        "metagame_event_id": "216",
        "type": "10",
        "duration_minutes": "30"
    },
    {
        "metagame_event_id": "217",
        "type": "10",
        "duration_minutes": "30"
    },
    {
        "metagame_event_id": "218",
        "type": "10",
        "duration_minutes": "30"
    },
    {
        "metagame_event_id": "219",
        "type": "10",
        "duration_minutes": "30"
    },
    {
        "metagame_event_id": "220",
        "type": "10",
        "duration_minutes": "30"
    },
    {
        "metagame_event_id": "221",
        "type": "10",
        "duration_minutes": "30"
    },
    {
        "metagame_event_id": "222",
        "type": "9",
        "experience_bonus": "25",
        "duration_minutes": "45"
    },
    {
        "metagame_event_id": "223",
        "type": "9",
        "experience_bonus": "25",
        "duration_minutes": "45"
    },
    {
        "metagame_event_id": "224",
        "type": "9",
        "experience_bonus": "25",
        "duration_minutes": "45"
    },
    {
        "metagame_event_id": "225",
        "type": "10",
        "duration_minutes": "30"
    },
    {
        "metagame_event_id": "226",
        "type": "9",
        "experience_bonus": "25",
        "duration_minutes": "45"
    },
    {
        "metagame_event_id": "227",
        "type": "9",
        "duration_minutes": "45"
    },
    {
        "metagame_event_id": "228",
        "type": "10",
        "duration_minutes": "30"
    },
    {
        "metagame_event_id": "229",
        "type": "10",
        "duration_minutes": "30"
    },
    {
        "metagame_event_id": "230",
        "type": "10",
        "duration_minutes": "30"
    },
    {
        "metagame_event_id": "231",
        "type": "10",
        "duration_minutes": "30"
    },
    {
        "metagame_event_id": "232",
        "type": "10",
        "duration_minutes": "30"
    },
    {
        "metagame_event_id": "233",
        "type": "6",
        "duration_minutes": "30"
    },
    {
        "metagame_event_id": "234",
        "type": "4",
        "duration_minutes": "20"
    },
    {
        "metagame_event_id": "235",
        "type": "10",
        "duration_minutes": "2"
    },
    {
        "metagame_event_id": "236",
        "type": "6",
        "duration_minutes": "15"
    },
    {
        "metagame_event_id": "237",
        "type": "6",
        "duration_minutes": "15"
    },
    {
        "metagame_event_id": "238",
        "type": "6",
        "duration_minutes": "15"
    },
    {
        "metagame_event_id": "239",
        "type": "6",
        "duration_minutes": "15"
    },
    {
        "metagame_event_id": "240",
        "type": "6",
        "duration_minutes": "10"
    },
    {
        "metagame_event_id": "241",
        "type": "6",
        "duration_minutes": "15"
    },
    {
        "metagame_event_id": "242",
        "type": "4",
        "duration_minutes": "15"
    },
    {
        "metagame_event_id": "243",
        "type": "4",
        "duration_minutes": "15"
    },
    {
        "metagame_event_id": "244",
        "type": "4",
        "duration_minutes": "15"
    },
    {
        "metagame_event_id": "245",
        "type": "4",
        "duration_minutes": "15"
    },
    {
        "metagame_event_id": "246",
        "type": "4",
        "duration_minutes": "15"
    },
    {
        "metagame_event_id": "248",
        "type": "9",
        "experience_bonus": "25",
        "duration_minutes": "30"
    },
    {
        "metagame_event_id": "249",
        "type": "9",
        "experience_bonus": "25",
        "duration_minutes": "30"
    },
    {
        "metagame_event_id": "250",
        "type": "9",
        "experience_bonus": "25",
        "duration_minutes": "30"
    },
    {
        "metagame_event_id": "251",
        "type": "4",
        "duration_minutes": "15"
    },
    {
        "metagame_event_id": "252",
        "type": "4",
        "duration_minutes": "15"
    },
    {
        "metagame_event_id": "253",
        "type": "4",
        "duration_minutes": "15"
    },
    {
        "metagame_event_id": "254",
        "type": "4",
        "duration_minutes": "15"
    },
    {
        "metagame_event_id": "255",
        "type": "4",
        "duration_minutes": "15"
    },
    {
        "metagame_event_id": "260",
        "type": "6",
        "duration_minutes": "5"
    }
]